DFBlocks/__init__.py
DFBlocks/cached_blocks.json
DFBlocks/dfdb.py
DFBlocks/temp_db.json
dfblocks-1.0.0.dist-info/LICENSE
dfblocks-1.0.0.dist-info/METADATA
dfblocks-1.0.0.dist-info/WHEEL
dfblocks-1.0.0.dist-info/RECORD
